pp_pripel/__init__.py
pp_pripel/attributeAnonymizier.py
pp_pripel/levenshtein.py
pp_pripel/pripel.py
pp_pripel/trace_variant_query.py
pp_pripel/tracematcher.py
pp_pripel-0.0.5.dist-info/License.txt
pp_pripel-0.0.5.dist-info/METADATA
pp_pripel-0.0.5.dist-info/WHEEL
pp_pripel-0.0.5.dist-info/top_level.txt
pp_pripel-0.0.5.dist-info/RECORD
