Metadata-Version: 2.1
Name: pp-pripel
Version: 0.0.5
Summary: Privacy-preserving Event Log Publishing with contextual Information
Home-page: https://github.com/samadeusfp/PRIPEL
Author: Stephan Fahrenkrog-Petersen
Author-email: fahrenks@hu-berlin.de
License: UNKNOWN
Project-URL: Source, https://github.com/samadeusfp/PRIPEL
Platform: UNKNOWN
Classifier: Programming Language :: Python :: 3
Classifier: License :: OSI Approved :: MIT License
Classifier: Operating System :: OS Independent
Requires-Dist: pm4py (==1.2.10)
Requires-Dist: diffprivlib (==0.3.0)
Requires-Dist: numpy (>=1.18.1)
Requires-Dist: scipy (>=1.5.2)
Requires-Dist: python-dateutil (>=2.8.1)
